README.rst
setup.py
src/Suds2Library/__init__.py
src/Suds2Library/clientmanagement.py
src/Suds2Library/factory.py
src/Suds2Library/options.py
src/Suds2Library/proxy.py
src/Suds2Library/soaplogging.py
src/Suds2Library/utils.py
src/Suds2Library/version.py
src/Suds2Library/wsse.py
src/robotframework_suds2library.egg-info/PKG-INFO
src/robotframework_suds2library.egg-info/SOURCES.txt
src/robotframework_suds2library.egg-info/dependency_links.txt
src/robotframework_suds2library.egg-info/requires.txt
src/robotframework_suds2library.egg-info/top_level.txt