Metadata-Version: 1.1
Name: robotframework-suds2library
Version: 1.1.1
Summary: Robot Framework test library for SOAP-based services.
Home-page: https://github.com/rticau/Suds2Library
Author: Mihai Parvu
Author-email: mihai-catalin.parvu@nokia.com
License: Apache License 2.0
Keywords: robotframework testing testautomation soap suds web service
Platform: any
Classifier: Development Status :: 5 - Production/Stable
Classifier: License :: OSI Approved :: Apache Software License
Classifier: Operating System :: OS Independent
Classifier: Programming Language :: Python :: 3.5
Classifier: Programming Language :: Python :: 3.6
Classifier: Programming Language :: Python :: 3.7
Classifier: Programming Language :: Python :: 3.8
Classifier: Topic :: Software Development :: Testing
